cdpchaosnetwork/__init__.py
cdpchaosnetwork/dns/__init__.py
cdpchaosnetwork/dns/actions.py
cdpchaosnetwork/dns/probes.py
cdpchaosnetwork/latency/__init__.py
cdpchaosnetwork/latency/actions.py
cdpchaosnetwork/latency/probes.py
cdpchaosnetwork/packetloss/__init__.py
cdpchaosnetwork/packetloss/actions.py
cdpchaosnetwork/packetloss/probes.py
cdpchaosnetwork/scripts/__init__.py
cdpchaosnetwork/scripts/endFailDns.sh
cdpchaosnetwork/scripts/endFailDnsSingleServer.sh
cdpchaosnetwork/scripts/startFailDns.sh
cdpchaosnetwork/scripts/startFailDnsSingleServer.sh
cdpchaosnetwork/utils/CPUActuator.py
cdpchaosnetwork/utils/ControllerThread.py
cdpchaosnetwork/utils/MonitorThread.py
cdpchaosnetwork/utils/RepeatedTimer.py
cdpchaosnetwork/utils/__init__.py
vztcdpchaos_network-1.6.4.dist-info/LICENSE
vztcdpchaos_network-1.6.4.dist-info/METADATA
vztcdpchaos_network-1.6.4.dist-info/WHEEL
vztcdpchaos_network-1.6.4.dist-info/top_level.txt
vztcdpchaos_network-1.6.4.dist-info/RECORD
