Metadata-Version: 2.1
Name: vztcdpchaos-network
Version: 1.6.4
Summary: Extension for creating network faults
Home-page: UNKNOWN
Author: vzt-cdp
License: Apache License Version 2.0
Platform: UNKNOWN
Classifier: License :: Freely Distributable
Classifier: Operating System :: OS Independent
Classifier: License :: OSI Approved :: Apache Software License
Classifier: Programming Language :: Python
Classifier: Programming Language :: Python :: 3
Classifier: Programming Language :: Python :: 3.5
Classifier: Programming Language :: Python :: 3.6
Classifier: Programming Language :: Python :: Implementation
Classifier: Programming Language :: Python :: Implementation :: CPython
Requires-Python: >=3.5.*
Requires-Dist: chaostoolkit-lib (>=1.7.0)
Requires-Dist: cdpchaostoolkit
Requires-Dist: logzero
Requires-Dist: psutil
